Metadata-Version: 2.1
Name: echoclean
Version: 0.1.0
Summary: Utility to help apply expert rules to sonobat output
Home-page: https://github.com/brendan-ward/echoclean
Author: Brendan C. Ward
Author-email: bcward@astutespruce.com
License: MIT
Keywords: sonobat,echolocation monitoring
Platform: UNKNOWN
Provides-Extra: test
